blitzcrop.py
blitzcrop-0.3.0.data/data/HISTORY.md
blitzcrop-0.3.0.data/data/LICENSE
blitzcrop-0.3.0.dist-info/LICENSE
blitzcrop-0.3.0.dist-info/METADATA
blitzcrop-0.3.0.dist-info/WHEEL
blitzcrop-0.3.0.dist-info/entry_points.txt
blitzcrop-0.3.0.dist-info/top_level.txt
blitzcrop-0.3.0.dist-info/zip-safe
blitzcrop-0.3.0.dist-info/RECORD
