Metadata-Version: 2.1
Name: blitzcrop
Version: 0.3.0
Summary: GUI for interactive batch image cropping.
Home-page: https://github.com/luphord/blitzcrop
Author: luphord
Author-email: luphord@protonmail.com
License: MIT license
Keywords: blitzcrop
Classifier: Development Status :: 3 - Alpha
Classifier: Intended Audience :: Developers
Classifier: License :: OSI Approved :: MIT License
Classifier: Natural Language :: English
Classifier: Programming Language :: Python :: 3
Classifier: Programming Language :: Python :: 3.8
Classifier: Programming Language :: Python :: 3.9
Classifier: Programming Language :: Python :: 3.10
Requires-Python: >=3.8
License-File: LICENSE
Requires-Dist: Pillow (==9.1.0)
